eapi/__init__.py
eapi/api.py
eapi/cli.py
eapi/environments.py
eapi/exceptions.py
eapi/messages.py
eapi/sessions.py
eapi/types.py
eapi/util.py
eapi_py-0.6.4.dist-info/METADATA
eapi_py-0.6.4.dist-info/WHEEL
eapi_py-0.6.4.dist-info/entry_points.txt
eapi_py-0.6.4.dist-info/top_level.txt
eapi_py-0.6.4.dist-info/RECORD
